QRClipboard/__init__.py
QRClipboard/main.py
qrclipboard-0.1.3.dist-info/METADATA
qrclipboard-0.1.3.dist-info/WHEEL
qrclipboard-0.1.3.dist-info/entry_points.txt
qrclipboard-0.1.3.dist-info/top_level.txt
qrclipboard-0.1.3.dist-info/RECORD
