Metadata-Version: 2.1
Name: qrclipboard
Version: 0.1.3
Summary: This script reads the content of the clipboard and displays it as a QR code.
Author-email: Friedjof Noweck <git@noweck.info>
License: MIT
Project-URL: Homepage, https://github.com/friedjof/QRClipboard
Project-URL: Documentation, https://github.com/friedjof/QRClipboard/blob/main/README.md
Project-URL: Source, https://github.com/friedjof/QRClipboard
Project-URL: Tracker, https://github.com/friedjof/QRClipboard/issues
Classifier: Programming Language :: Python :: 3
Classifier: License :: OSI Approved :: MIT License
Classifier: Operating System :: OS Independent
Requires-Python: >=3.6
Requires-Dist: pyperclip
Requires-Dist: qrcode[pil]
Requires-Dist: validators>=0.33.0
